{
  "epic": "10080",
  "stories": {
    "Task Creation and Listing": "10085",
    "Task Lifecycle Management": "10086",
    "Design and implement responsive dark-themed login page UI": "10119",
    "Implement email input field with basic functionality": "10120",
    "Implement password input field with masked entry": "10121",
    "Implement email format validation": "10122",
    "Implement password minimum length validation": "10123",
    "Implement login button and form submission": "10124",
    "Display Initial Counter Value": "10125",
    "Render Counter Increment Button": "10126",
    "Increment Counter on Button Click": "10127",
    "Update Displayed Counter Value": "10128",
    "As a user, I want to see a login form with email and password input fields, so that I can enter my credentials.": "10162",
    "As a user, I want the login form to have a sleek dark theme, so that I have a modern and visually appealing experience.": "10163",
    "As a user, when I enter an invalid email format, I want to see an error message, so that I can correct my input.": "10164",
    "As a user, when I enter a password shorter than 6 characters, I want to see an error message, so that I can correct my input.": "10165",
    "Display Todo Checklist Page": "10166",
    "Display Task Input Field and Add Button": "10167",
    "Type Task into Input Field": "10168",
    "Add Task to List": "10169",
    "Clear Input Field After Adding Task": "10170"
  }
}